{
  "type": "AnnotationPage",
  "@context": [
    "http://www.w3.org/ns/anno.jsonld"
  ],
  "items": [
    {
      "id": "c7c0af435bb22863",
      "type": "Annotation",
      "@context": [
        "http://www.w3.org/ns/anno.jsonld",
        "http://geojson.org/geojson-ld/geojson-context.jsonld",
        "http://iiif.io/api/presentation/3/context.json"
      ],
      "motivation": "georeferencing",
      "target": {
        "type": "Image",
        "source": "https://dlc.services/iiif-img/7/34/447ef427a7b48240dfd78e2f5d318eb2/full/full/0/default.jpg",
        "service": [
          {
            "@id": "https://dlc.services/iiif-img/7/34/447ef427a7b48240dfd78e2f5d318eb2",
            "type": "ImageService2"
          }
        ],
        "selector": {
          "type": "SvgSelector",
          "value": "<svg width=\"3045\" height=\"4311\"><polygon points=\"101,784 473,1465 92,1465 88,1632 565,1634 705,1890 144,2207 137,3854 2869,3868 2870,1636 2960,1636 2960,1469 2869,1469 2870,137 2210,138\" /></svg>"
        }
      },
      "body": {
        "type": "FeatureCollection",
        "purpose": "gcp-georeferencing",
        "transformation": {
          "type": "polynomial",
          "order": 0
        },
        "features": [
          {
            "type": "Feature",
            "properties": {
              "pixelCoords": [
                1210,
                1349
              ]
            },
            "geometry": {
              "type": "Point",
              "coordinates": [
                4.9784818,
                52.3187031
              ]
            }
          },
          {
            "type": "Feature",
            "properties": {
              "pixelCoords": [
                631,
                1349
              ]
            },
            "geometry": {
              "type": "Point",
              "coordinates": [
                4.9776963,
                52.3195749
              ]
            }
          },
          {
            "type": "Feature",
            "properties": {
              "pixelCoords": [
                2132,
                1997
              ]
            },
            "geometry": {
              "type": "Point",
              "coordinates": [
                4.9781501,
                52.3167796
              ]
            }
          }
        ]
      }
    }
  ]
}