{
  "type": "AnnotationPage",
  "@context": [
    "http://www.w3.org/ns/anno.jsonld"
  ],
  "items": [
    {
      "id": "749b713c1e5dc2ca",
      "type": "Annotation",
      "@context": [
        "http://www.w3.org/ns/anno.jsonld",
        "http://geojson.org/geojson-ld/geojson-context.jsonld",
        "http://iiif.io/api/presentation/3/context.json"
      ],
      "motivation": "georeferencing",
      "target": {
        "type": "Image",
        "source": "https://stadsarchiefamsterdam.memorix.io/resources/records/media/0d70e3e6-1501-b919-1b94-c69720c4397f/iiif/3/30018684/full/max/0/default.jpg",
        "service": [
          {
            "@id": "https://stadsarchiefamsterdam.memorix.io/resources/records/media/0d70e3e6-1501-b919-1b94-c69720c4397f/iiif/3/30018684",
            "type": "ImageService3"
          }
        ],
        "selector": {
          "type": "SvgSelector",
          "value": "<svg width=\"4961\" height=\"3508\"><polygon points=\"558,655 561,322 808,324 1586,541 1621,552 1653,562 1706,576 1851,614 2083,680 2055,782 1740,1984 1677,2216 1616,2447 1598,2512 1582,2520 1333,2511 528,2495\" /></svg>"
        }
      },
      "body": {
        "type": "FeatureCollection",
        "purpose": "gcp-georeferencing",
        "transformation": {
          "type": "polynomial",
          "order": 0
        },
        "features": [
          {
            "type": "Feature",
            "properties": {
              "pixelCoords": [
                717,
                656
              ]
            },
            "geometry": {
              "type": "Point",
              "coordinates": [
                4.8316141,
                52.3805407
              ]
            }
          },
          {
            "type": "Feature",
            "properties": {
              "pixelCoords": [
                1491,
                2399
              ]
            },
            "geometry": {
              "type": "Point",
              "coordinates": [
                4.8319183,
                52.380126
              ]
            }
          },
          {
            "type": "Feature",
            "properties": {
              "pixelCoords": [
                1744,
                1069
              ]
            },
            "geometry": {
              "type": "Point",
              "coordinates": [
                4.8320055,
                52.3804446
              ]
            }
          },
          {
            "type": "Feature",
            "properties": {
              "pixelCoords": [
                593,
                656
              ]
            },
            "geometry": {
              "type": "Point",
              "coordinates": [
                4.8315301,
                52.3805403
              ]
            }
          },
          {
            "type": "Feature",
            "properties": {
              "pixelCoords": [
                717,
                1796
              ]
            },
            "geometry": {
              "type": "Point",
              "coordinates": [
                4.8315859,
                52.3802677
              ]
            }
          },
          {
            "type": "Feature",
            "properties": {
              "pixelCoords": [
                1832,
                756
              ]
            },
            "geometry": {
              "type": "Point",
              "coordinates": [
                4.8320369,
                52.3805221
              ]
            }
          },
          {
            "type": "Feature",
            "properties": {
              "pixelCoords": [
                1509,
                1915
              ]
            },
            "geometry": {
              "type": "Point",
              "coordinates": [
                4.8319206,
                52.3802442
              ]
            }
          }
        ]
      }
    }
  ]
}