{
  "type": "AnnotationPage",
  "@context": [
    "http://www.w3.org/ns/anno.jsonld"
  ],
  "items": [
    {
      "id": "6cb8acb6b0100df2",
      "type": "Annotation",
      "@context": [
        "http://www.w3.org/ns/anno.jsonld",
        "http://geojson.org/geojson-ld/geojson-context.jsonld",
        "http://iiif.io/api/presentation/3/context.json"
      ],
      "motivation": "georeferencing",
      "target": {
        "type": "Image",
        "source": "https://dlc.services/iiif-img/7/33/649b8cc6-99fc-443d-8918-9ee9b4ff5436/full/full/0/default.jpg",
        "service": [
          {
            "@id": "https://dlc.services/iiif-img/7/33/649b8cc6-99fc-443d-8918-9ee9b4ff5436",
            "type": "ImageService2"
          }
        ],
        "selector": {
          "type": "SvgSelector",
          "value": "<svg width=\"1500\" height=\"1172\"><polygon points=\"42,18 23,38 25,569 30,1149 564,1149 608,1066 639,1035 634,1021 669,972 688,968 726,901 731,884 756,865 771,870 786,877 805,960 831,991 859,1033 891,1062 895,1099 911,1146 1202,1145 1466,1142 1477,758 1464,783 1450,790 1442,741 1424,675 1427,616 1456,611 1469,630 1478,650 1481,407 1487,93 1476,89 1470,42 1470,26 474,19 457,28 391,38 372,24\" /></svg>"
        }
      },
      "body": {
        "type": "FeatureCollection",
        "purpose": "gcp-georeferencing",
        "transformation": {
          "type": "polynomial",
          "order": 0
        },
        "features": [
          {
            "type": "Feature",
            "properties": {
              "pixelCoords": [
                823,
                573
              ]
            },
            "geometry": {
              "type": "Point",
              "coordinates": [
                4.4323545,
                51.9242062
              ]
            }
          },
          {
            "type": "Feature",
            "properties": {
              "pixelCoords": [
                400,
                790
              ]
            },
            "geometry": {
              "type": "Point",
              "coordinates": [
                4.4337212,
                51.9230275
              ]
            }
          },
          {
            "type": "Feature",
            "properties": {
              "pixelCoords": [
                287,
                694
              ]
            },
            "geometry": {
              "type": "Point",
              "coordinates": [
                4.4331918,
                51.9226256
              ]
            }
          },
          {
            "type": "Feature",
            "properties": {
              "pixelCoords": [
                1013,
                455
              ]
            },
            "geometry": {
              "type": "Point",
              "coordinates": [
                4.4314997,
                51.9247445
              ]
            }
          }
        ]
      }
    }
  ]
}
