{
  "type": "AnnotationPage",
  "@context": [
    "http://www.w3.org/ns/anno.jsonld"
  ],
  "items": [
    {
      "id": "aced2df6104ae3b6",
      "type": "Annotation",
      "@context": [
        "http://www.w3.org/ns/anno.jsonld",
        "http://geojson.org/geojson-ld/geojson-context.jsonld",
        "http://iiif.io/api/presentation/3/context.json"
      ],
      "motivation": "georeferencing",
      "target": {
        "type": "Image",
        "source": "https://dlc.services/iiif-img/7/33/b0839c10-e022-4693-9542-d95e2a0c2048/full/full/0/default.jpg",
        "service": [
          {
            "@id": "https://dlc.services/iiif-img/7/33/b0839c10-e022-4693-9542-d95e2a0c2048",
            "type": "ImageService2"
          }
        ],
        "selector": {
          "type": "SvgSelector",
          "value": "<svg width=\"5790\" height=\"3308\"><polygon points=\"0,0 0,3308 5790,3308 5790,0\" /></svg>"
        }
      },
      "body": {
        "type": "FeatureCollection",
        "purpose": "gcp-georeferencing",
        "transformation": {
          "type": "polynomial",
          "order": 0
        },
        "features": [
          {
            "type": "Feature",
            "properties": {
              "pixelCoords": [
                4807,
                1075
              ]
            },
            "geometry": {
              "type": "Point",
              "coordinates": [
                5.6860659,
                51.9012876
              ]
            }
          },
          {
            "type": "Feature",
            "properties": {
              "pixelCoords": [
                717,
                1163
              ]
            },
            "geometry": {
              "type": "Point",
              "coordinates": [
                5.6340563,
                51.9002734
              ]
            }
          },
          {
            "type": "Feature",
            "properties": {
              "pixelCoords": [
                2384,
                326
              ]
            },
            "geometry": {
              "type": "Point",
              "coordinates": [
                5.6555058,
                51.9068907
              ]
            }
          }
        ]
      }
    }
  ]
}
