{
  "type": "AnnotationPage",
  "@context": [
    "http://www.w3.org/ns/anno.jsonld"
  ],
  "items": [
    {
      "id": "3c403868e96d0fb7",
      "type": "Annotation",
      "@context": [
        "http://www.w3.org/ns/anno.jsonld",
        "http://geojson.org/geojson-ld/geojson-context.jsonld",
        "http://iiif.io/api/presentation/3/context.json"
      ],
      "motivation": "georeferencing",
      "target": {
        "type": "Image",
        "source": "https://dlc.services/iiif-img/7/34/509e05d2beebd95a7d40e29a99b7ccd9/full/full/0/default.jpg",
        "service": [
          {
            "@id": "https://dlc.services/iiif-img/7/34/509e05d2beebd95a7d40e29a99b7ccd9",
            "type": "ImageService2"
          }
        ],
        "selector": {
          "type": "SvgSelector",
          "value": "<svg width=\"3045\" height=\"4311\"><polygon points=\"177,2257 1632,769 2921,1574 2922,2084 2088,2835 2377,3148 2381,3526 1980,3524 1679,3202 328,2503\" /></svg>"
        }
      },
      "body": {
        "type": "FeatureCollection",
        "purpose": "gcp-georeferencing",
        "transformation": {
          "type": "polynomial",
          "order": 0
        },
        "features": [
          {
            "type": "Feature",
            "properties": {
              "pixelCoords": [
                451,
                2364
              ]
            },
            "geometry": {
              "type": "Point",
              "coordinates": [
                4.9023406,
                52.3700984
              ]
            }
          },
          {
            "type": "Feature",
            "properties": {
              "pixelCoords": [
                2564,
                1466
              ]
            },
            "geometry": {
              "type": "Point",
              "coordinates": [
                4.908604,
                52.3710026
              ]
            }
          },
          {
            "type": "Feature",
            "properties": {
              "pixelCoords": [
                2167,
                1613
              ]
            },
            "geometry": {
              "type": "Point",
              "coordinates": [
                4.9074118,
                52.3708654
              ]
            }
          },
          {
            "type": "Feature",
            "properties": {
              "pixelCoords": [
                1032,
                2726
              ]
            },
            "geometry": {
              "type": "Point",
              "coordinates": [
                4.9037496,
                52.3693409
              ]
            }
          }
        ]
      }
    }
  ]
}